{
  "id": "131a4a32-f3b3-4dc8-b379-8d1f72e2e4b1",
  "description": "S17",
  "createdAt": "2026-03-06T23:26:29.348Z",
  "closed": false,
  "promptHistory": [
    {
      "id": "1772854853859",
      "text": "Is delphi still used",
      "timestamp": "2026-03-07T03:40:53.859Z",
      "tokens": 5
    }
  ],
  "contextHistory": [
    {
      "id": "1772854837416",
      "text": "We aere talking about software languages",
      "timestamp": "2026-03-07T03:40:37.416Z",
      "tokens": 10
    }
  ],
  "contextText": "We aere talking about software languages",
  "flags": {}
}